rating/__init__.py
rating/admin.py
rating/apps.py
rating/models.py
rating/settings.py
rating/tests.py
rating/urls.py
rating/views.py
rating/migrations/0001_initial.py
rating/migrations/0002_config.py
rating/migrations/__init__.py
rating/static/rating/css/rating.css
rating/static/rating/css/rating.min.css
rating/static/rating/img/heart.svg
rating/static/rating/img/star.svg
rating/static/rating/js/rating.js
rating/static/rating/js/rating.min.js
rating/templates/rating/info/info_base.html
rating/templates/rating/info/info_extender.html
rating/templates/rating/rating/rating.html
rating/templates/rating/rating/rating_info.html
rating/templates/rating/utils/IMPORTS.html
rating/templates/rating/utils/SCRIPTS.html
rating/templatetags/__init__.py
rating/templatetags/rating_tags.py
django_rating_system-1.1.1.dist-info/LICENSE
django_rating_system-1.1.1.dist-info/METADATA
django_rating_system-1.1.1.dist-info/WHEEL
django_rating_system-1.1.1.dist-info/top_level.txt
django_rating_system-1.1.1.dist-info/RECORD
