Metadata-Version: 2.1
Name: django-rating-system
Version: 1.1.1
Summary: Django rating System, It can be associated with any given model.
Home-page: https://github.com/mahyar-amiri/django-rating-system
Author: Mahyar Amiri
Author-email: mmaahhyyaarr@gmail.com
License: MIT
Project-URL: Documentation, https://github.com/mahyar-amiri/django-rating-system/README.md
Project-URL: Source Code, https://github.com/mahyar-amiri/django-rating-system
Keywords: django rating rating-system django-rating ratings ratings-system django-ratings ajax
License-File: LICENSE
Requires-Dist: django
Requires-Dist: pillow
Requires-Dist: requests
Provides-Extra: markdown
Requires-Dist: markdown ; extra == 'markdown'
